pysqueezebox/__init__.py
pysqueezebox/const.py
pysqueezebox/discovery.py
pysqueezebox/player.py
pysqueezebox/server.py
pysqueezebox-0.13.0.dist-info/licenses/LICENSE
pysqueezebox-0.13.0.dist-info/METADATA
pysqueezebox-0.13.0.dist-info/WHEEL
pysqueezebox-0.13.0.dist-info/top_level.txt
pysqueezebox-0.13.0.dist-info/RECORD
