Metadata-Version: 2.4
Name: pysqueezebox
Version: 0.13.0
Summary: Asynchronous library to control Logitech Media Server
Author-email: Raj Laud <raj.laud@gmail.com>
Project-URL: Homepage, https://github.com/rajlaud/pysqueezebox
Project-URL: Repository, https://github.com/rajlaud/pysqueezebox.git
Classifier: License :: OSI Approved :: Apache Software License
Requires-Python: >=3.11
License-File: LICENSE
Requires-Dist: aiohttp
Dynamic: license-file
